[
  {
    "message": "hiiiiiiiiii",
    "date": "2025-05-03T10:05:07.041Z"
  },
  {
    "message": "ggfuhgfg\n",
    "date": "2025-05-03T10:07:43.760Z"
  },
  {
    "message": "hhhhh",
    "date": "2025-05-03T10:07:52.740Z"
  },
  {
    "message": "rgrgr",
    "date": "2025-05-03T10:09:13.605Z"
  },
  {
    "message": "hiii\n",
    "date": "2025-05-03T10:10:57.887Z"
  },
  {
    "message": "hiii",
    "date": "2025-05-03T10:11:25.422Z"
  },
  {
    "message": "or bha \n",
    "date": "2025-05-03T10:11:36.255Z"
  },
  {
    "message": "fgg\n\n\n",
    "date": "2025-05-03T10:15:00.606Z"
  }
]